Komponenten/Registerfile/register_file.vhdl
-- Laboratory RA solutions/versuch2
-- Sommersemester 25
-- Group Details
-- Lab Date: 06.05.2005
-- 1. Participant First and Last Name: Baran Ali Sönmez
-- 2. Participant First and Last Name: Mashal Khan

library ieee;
use ieee.std_logic_1164.all;
use ieee.numeric_std.all;
use ieee.math_real.all;
use work.constant_package.all;

entity register_file is
    generic (
        word_width : integer := WORD_WIDTH;
        adr_width : integer := REG_ADR_WIDTH;
        reg_amount : integer := 2 ** REG_ADR_WIDTH
    );
    port (
        pi_clk, pi_rst, pi_writeEnable : in std_logic := '0';
        pi_readRegAddr1 : in std_logic_vector(adr_width - 1 downto 0) := (others => '0');
        pi_readRegAddr2 : in std_logic_vector(adr_width - 1 downto 0) := (others => '0');
        pi_writeRegAddr : in std_logic_vector(adr_width - 1 downto 0) := (others => '0');
        pi_writeRegData : in std_logic_vector(word_width - 1 downto 0) := (others => '0');
        po_readRegData1 : out std_logic_vector(word_width - 1 downto 0) := (others => '0');
        po_readRegData2 : out std_logic_vector(word_width - 1 downto 0) := (others => '0')
    );
end entity register_file;

architecture behavior of register_file is
    type registermemory is array (0 to reg_amount - 1) of std_logic_vector(word_width - 1 downto 0);
    signal reg_array : registermemory := (others => (others => '0'));
begin
    process (pi_clk, pi_rst)
    begin
        if pi_rst = '1' then
            po_readRegData1 <= (others => '0');
            po_readRegData2 <= (others => '0');
            reg_array <= (others => (others => '0'));
        elsif rising_edge(pi_clk) then
            po_readRegData1 <= reg_array(to_integer(unsigned(pi_readRegAddr1)));
            po_readRegData2 <= reg_array(to_integer(unsigned(pi_readRegAddr2)));
            if pi_writeEnable = '1' then
                reg_array(to_integer(unsigned(pi_writeRegAddr))) <= pi_writeRegData;
            end if;
        end if;
    end process;
end architecture behavior;

Testbenches/Registerfile/register_file_tb.vhdl
-- Laboratory RA solutions/versuch2
-- Sommersemester 25
-- Group Details
-- Lab Date: 06.05.2005
-- 1. Participant First and Last Name: Baran Ali Sönmez
-- 2. Participant First and Last Name: Mashal Khan

library ieee;
use ieee.std_logic_1164.all;
use ieee.numeric_std.all;
use ieee.math_real.all;
use work.constant_package.all;

entity register_file_tb is
end entity register_file_tb;

architecture behavior of register_file_tb is

    signal s_clk : std_logic := '0';
    signal s_rst : std_logic := '0';
    signal s_we : std_logic := '0';
    signal s_readRegAddr1 : std_logic_vector(REG_ADR_WIDTH - 1 downto 0) := (others => '0');
    signal s_readRegAddr2 : std_logic_vector(REG_ADR_WIDTH - 1 downto 0) := (others => '0');
    signal s_writeRegAddr : std_logic_vector(REG_ADR_WIDTH - 1 downto 0) := (others => '0');
    signal s_writeRegData : std_logic_vector(16 - 1 downto 0) := (others => '0');
    signal s_readRegData1 : std_logic_vector(16 - 1 downto 0) := (others => '0');
    signal s_readRegData2 : std_logic_vector(16 - 1 downto 0) := (others => '0');
    signal s_writeRegData_32 : std_logic_vector(WORD_WIDTH - 1 downto 0) := (others => '0');
    signal s_readRegData1_32 : std_logic_vector(WORD_WIDTH - 1 downto 0) := (others => '0');
    signal s_readRegData2_32 : std_logic_vector(WORD_WIDTH - 1 downto 0) := (others => '0');

    -- Taktprozess für Simulation
    constant clk_period : time := 10 ns;
begin
    clk_process : process
    begin
        s_clk <= '0';
        wait for clk_period / 2;
        s_clk <= '1';
        wait for clk_period / 2;
    end process;

    -- Instanz des RAM-Moduls
    dut1 : entity work.register_file
        generic map(16)
        port map(
            pi_clk => s_clk,
            pi_rst => s_rst, -- Reset wird hier uebergeben
            pi_writeEnable => s_we,
            pi_readRegAddr1 => s_readRegAddr1,
            pi_readRegAddr2 => s_readRegAddr2,
            pi_writeRegAddr => s_writeRegAddr,
            pi_writeRegData => s_writeRegData,
            po_readRegData1 => s_readRegData1,
            po_readRegData2 => s_readRegData2
        );

    dut2 : entity work.register_file
        generic map(32)
        port map(
            pi_clk => s_clk,
            pi_rst => s_rst, -- Reset wird hier uebergeben
            pi_writeEnable => s_we,
            pi_readRegAddr1 => s_readRegAddr1,
            pi_readRegAddr2 => s_readRegAddr2,
            pi_writeRegAddr => s_writeRegAddr,
            pi_writeRegData => s_writeRegData_32,
            po_readRegData1 => s_readRegData1_32,
            po_readRegData2 => s_readRegData2_32
        );

    -- Testprozess mit Assertions
    test_process : process
    begin
        -- Reset setzten
        s_rst <= '1';
        wait for clk_period;
        s_rst <= '0';

        -- Test 1: Versuchen die 0 Vektoren zu lesen
        s_readRegAddr1 <= "00001";
        s_readRegAddr2 <= "00010";
        s_writeRegAddr <= "00011";
        s_writeRegData <= "0000000010100101";
        s_writeRegData_32 <= "00000000000000000000000010100101"; -- 0xA5
        wait for clk_period;
        assert (s_readRegData1 = "0000000000000000") report "Reading Out1 after reset not right" severity error;
        assert (s_readRegData2 = "0000000000000000") report "Reading Out2 after reset not right" severity error;
        assert (s_readRegData1_32 = "00000000000000000000000000000000") report "Reading Out1_32 after reset not right" severity error;
        assert (s_readRegData2_32 = "00000000000000000000000000000000") report "Reading Out2_32 after reset not right" severity error;

        -- Schreiben von 0xA5 in Register 0x4
        s_we <= '1';
        wait for clk_period;
        s_we <= '0';

        -- Test 2: Versuchen die geschriebenen 0x4 Adresse zu lesen
        s_readRegAddr1 <= "00011";
        wait for clk_period;
        assert (s_readRegData1 = "0000000010100101") report "Reading Out1 after writing not right" severity error;
        assert (s_readRegData2 = "0000000000000000") report "Reading Out2 after writing not right" severity error;
        assert (s_readRegData1_32 = "00000000000000000000000010100101") report "Reading Out1_32 after writing not right" severity error;
        assert (s_readRegData2_32 = "00000000000000000000000000000000") report "Reading Out2_32 after writing not right" severity error;

        -- Schreiben von 0x1 in Register 0x1
        s_writeRegAddr <= "00001";
        s_writeRegData <= "0000000000000001";
        s_writeRegData_32 <= "00000000000000000000000000000001";
        s_we <= '1';
        wait for clk_period;
        s_readRegAddr2 <= "00001";
        wait for clk_period;

        -- Test 3: Versuchen die geschriebenen Werte in Out2 auszugeben
        assert (s_readRegData1 = "0000000010100101") report "Reading Out1 after number 2 writing not right" severity error;
        assert (s_readRegData2 = "0000000000000001") report "Reading Out2 after number 2 writing not right" severity error;
        assert (s_readRegData1_32 = "00000000000000000000000010100101") report "Reading Out1_32 after number 2 writing not right" severity error;
        assert (s_readRegData2_32 = "00000000000000000000000000000001") report "Reading Out2_32 after writing number 2 not right" severity error;

        -- Nochmals reset testen
        s_rst <= '1';
        wait for clk_period;
        s_rst <= '0';
        assert (s_readRegData1 = "0000000000000000") report "Reading Out1 after reset not right" severity error;
        assert (s_readRegData2 = "0000000000000000") report "Reading Out2 after reset not right" severity error;
        assert (s_readRegData1_32 = "00000000000000000000000000000000") report "Reading Out1_32 after reset not right" severity error;
        assert (s_readRegData2_32 = "00000000000000000000000000000000") report "Reading Out2_32 after reset not right" severity error;

        report "Alle Tests erfolgreich abgeschlossen." severity note;

        wait;
    end process;
end architecture behavior;

Skripts/Registerfile/register_file_tb.vcd
$date
  Mon May  5 20:33:36 2025
$end
$version
  GHDL v0
$end
$timescale
  1 fs
$end
$scope module standard $end
$upscope $end
$scope module textio $end
$upscope $end
$scope module std_logic_1164 $end
$upscope $end
$scope module numeric_std $end
$upscope $end
$scope module math_real $end
$upscope $end
$scope module constant_package $end
$upscope $end
$scope module register_file_tb $end
$var reg 1 ! s_clk $end
$var reg 1 " s_rst $end
$var reg 1 # s_we $end
$var reg 5 $ s_readregaddr1[4:0] $end
$var reg 5 % s_readregaddr2[4:0] $end
$var reg 5 & s_writeregaddr[4:0] $end
$var reg 16 ' s_writeregdata[15:0] $end
$var reg 16 ( s_readregdata1[15:0] $end
$var reg 16 ) s_readregdata2[15:0] $end
$var reg 32 * s_writeregdata_32[31:0] $end
$var reg 32 + s_readregdata1_32[31:0] $end
$var reg 32 , s_readregdata2_32[31:0] $end
$scope module dut1 $end
$var reg 1 - pi_clk $end
$var reg 1 . pi_rst $end
$var reg 1 / pi_writeenable $end
$var reg 5 0 pi_readregaddr1[4:0] $end
$var reg 5 1 pi_readregaddr2[4:0] $end
$var reg 5 2 pi_writeregaddr[4:0] $end
$var reg 16 3 pi_writeregdata[15:0] $end
$var reg 16 4 po_readregdata1[15:0] $end
$var reg 16 5 po_readregdata2[15:0] $end
$comment reg_array is not handled $end
$upscope $end
$scope module dut2 $end
$var reg 1 6 pi_clk $end
$var reg 1 7 pi_rst $end
$var reg 1 8 pi_writeenable $end
$var reg 5 9 pi_readregaddr1[4:0] $end
$var reg 5 : pi_readregaddr2[4:0] $end
$var reg 5 ; pi_writeregaddr[4:0] $end
$var reg 32 < pi_writeregdata[31:0] $end
$var reg 32 = po_readregdata1[31:0] $end
$var reg 32 > po_readregdata2[31:0] $end
$comment reg_array is not handled $end
$upscope $end
$upscope $end
$enddefinitions $end
#0
0!
1"
0#
b00000 $
b00000 %
b00000 &
b0000000000000000 '
b0000000000000000 (
b0000000000000000 )
b00000000000000000000000000000000 *
b00000000000000000000000000000000 +
b00000000000000000000000000000000 ,
0-
1.
0/
b00000 0
b00000 1
b00000 2
b0000000000000000 3
b0000000000000000 4
b0000000000000000 5
06
17
08
b00000 9
b00000 :
b00000 ;
b00000000000000000000000000000000 <
b00000000000000000000000000000000 =
b00000000000000000000000000000000 >
#5000000
1!
1-
16
#10000000
0!
0"
b00001 $
b00010 %
b00011 &
b0000000010100101 '
b00000000000000000000000010100101 *
0-
0.
b00001 0
b00010 1
b00011 2
b0000000010100101 3
06
07
b00001 9
b00010 :
b00011 ;
b00000000000000000000000010100101 <
#15000000
1!
1-
16
#20000000
0!
1#
0-
1/
06
18
#25000000
1!
1-
16
#30000000
0!
0#
b00011 $
0-
0/
b00011 0
06
08
b00011 9
#35000000
1!
b0000000010100101 (
b00000000000000000000000010100101 +
1-
b0000000010100101 4
16
b00000000000000000000000010100101 =
#40000000
0!
1#
b00001 &
b0000000000000001 '
b00000000000000000000000000000001 *
0-
1/
b00001 2
b0000000000000001 3
06
18
b00001 ;
b00000000000000000000000000000001 <
#45000000
1!
1-
16
#50000000
0!
b00001 %
0-
b00001 1
06
b00001 :
#55000000
1!
b0000000000000001 )
b00000000000000000000000000000001 ,
1-
b0000000000000001 5
16
b00000000000000000000000000000001 >
#60000000
0!
1"
b0000000000000000 (
b0000000000000000 )
b00000000000000000000000000000000 +
b00000000000000000000000000000000 ,
0-
1.
b0000000000000000 4
b0000000000000000 5
06
17
b00000000000000000000000000000000 =
b00000000000000000000000000000000 >
#65000000
1!
1-
16
#70000000
0!
0"
0-
0.
06
07
#75000000
1!
1-
16
#80000000
0!
0-
06
#85000000
1!
b0000000000000001 )
b00000000000000000000000000000001 ,
1-
b0000000000000001 5
16
b00000000000000000000000000000001 >
