Komponenten/Registerfile/register_file.vhdl
-- Laboratory RA solutions/versuch2
-- Sommersemester 25
-- Group Details
-- Lab Date: 06.05.2005
-- 1. Participant First and Last Name: Baran Ali Sönmez
-- 2. Participant First and Last Name: Mashal Khan

library ieee;
use ieee.std_logic_1164.all;
use ieee.numeric_std.all;
use ieee.math_real.all;
use work.constant_package.all;
use work.types.all;

entity register_file is
    generic (
        word_width : integer := WORD_WIDTH;
        adr_width : integer := REG_ADR_WIDTH;
        reg_amount : integer := 2 ** REG_ADR_WIDTH
    );
    port (
        pi_clk, pi_rst, pi_writeEnable : in std_logic := '0';
        pi_readRegAddr1 : in std_logic_vector(adr_width - 1 downto 0) := (others => '0');
        pi_readRegAddr2 : in std_logic_vector(adr_width - 1 downto 0) := (others => '0');
        pi_writeRegAddr : in std_logic_vector(adr_width - 1 downto 0) := (others => '0');
        pi_writeRegData : in std_logic_vector(word_width - 1 downto 0) := (others => '0');
        po_readRegData1 : out std_logic_vector(word_width - 1 downto 0) := (others => '0');
        po_readRegData2 : out std_logic_vector(word_width - 1 downto 0) := (others => '0');
        po_registerOut : out registerMemory := (others => (others => '0'))
    );
end entity register_file;

architecture behavior of register_file is

    -- type registermemory is array (0 to reg_amount - 1) of std_logic_vector(word_width - 1 downto 0);
    signal reg_array : registerMemory := (
        1 => std_logic_vector(to_unsigned(9, WORD_WIDTH)), -- x1 = 9
        2 => std_logic_vector(to_unsigned(8, WORD_WIDTH)), -- x2 = 8
        others => (others => '0'));

begin
    process (pi_clk, pi_rst) -- Registerfile implementiert
    begin
        if pi_rst = '1' then -- Reset
            po_readRegData1 <= (others => '0');
            po_readRegData2 <= (others => '0');
            reg_array <= (others => (others => '0'));
            reg_array(1) <= std_logic_vector(to_unsigned(9, WORD_WIDTH));
            reg_array(2) <= std_logic_vector(to_unsigned(8, WORD_WIDTH));
        elsif rising_edge(pi_clk) then -- Output
            po_readRegData1 <= reg_array(to_integer(unsigned(pi_readRegAddr1)));
            po_readRegData2 <= reg_array(to_integer(unsigned(pi_readRegAddr2)));
            po_registerOut <= reg_array;
            if pi_writeEnable = '1' and to_integer(unsigned(pi_writeRegAddr)) /= 0 then -- Writing
                reg_array(to_integer(unsigned(pi_writeRegAddr))) <= pi_writeRegData;
            end if;
        end if;
    end process;
end architecture behavior;

Testbenches/Registerfile/register_file_tb.vhdl
-- Laboratory RA solutions/versuch2
-- Sommersemester 25
-- Group Details
-- Lab Date: 06.05.2005
-- 1. Participant First and Last Name: Baran Ali Sönmez
-- 2. Participant First and Last Name: Mashal Khan

library ieee;
use ieee.std_logic_1164.all;
use ieee.numeric_std.all;
use ieee.math_real.all;
use work.constant_package.all;

entity register_file_tb is
end entity register_file_tb;

architecture behavior of register_file_tb is

    signal s_clk : std_logic := '0';
    signal s_rst : std_logic := '0';
    signal s_we : std_logic := '0';
    signal s_readRegAddr1 : std_logic_vector(REG_ADR_WIDTH - 1 downto 0) := (others => '0');
    signal s_readRegAddr2 : std_logic_vector(REG_ADR_WIDTH - 1 downto 0) := (others => '0');
    signal s_writeRegAddr : std_logic_vector(REG_ADR_WIDTH - 1 downto 0) := (others => '0');
    --signal s_writeRegData : std_logic_vector(16 - 1 downto 0) := (others => '0');
    --signal s_readRegData1 : std_logic_vector(16 - 1 downto 0) := (others => '0');
    --signal s_readRegData2 : std_logic_vector(16 - 1 downto 0) := (others => '0');
    signal s_writeRegData_32 : std_logic_vector(WORD_WIDTH - 1 downto 0) := (others => '0');
    signal s_readRegData1_32 : std_logic_vector(WORD_WIDTH - 1 downto 0) := (others => '0');
    signal s_readRegData2_32 : std_logic_vector(WORD_WIDTH - 1 downto 0) := (others => '0');

    -- Taktprozess für Simulation
    constant clk_period : time := 10 ns;
begin
    clk_process : process
    begin
        s_clk <= '0';
        wait for clk_period / 2;
        s_clk <= '1';
        wait for clk_period / 2;
    end process;

    -- Instanz des RAM-Moduls
 --   dut1 : entity work.register_file
 --       generic map(16, REG_ADR_WIDTH)
 --       port map(
  --          pi_clk => s_clk,
   --         pi_rst => s_rst, -- Reset wird hier uebergeben
     --       pi_writeEnable => s_we,
       --     pi_readRegAddr1 => s_readRegAddr1,
         --  pi_readRegAddr2 => s_readRegAddr2,
         --   pi_writeRegAddr => s_writeRegAddr,
--            pi_writeRegData => s_writeRegData,
  --          po_readRegData1 => s_readRegData1,
    --        po_readRegData2 => s_readRegData2
      --  );

    dut2 : entity work.register_file
        generic map(32, REG_ADR_WIDTH)
        port map(
            pi_clk => s_clk,
            pi_rst => s_rst, -- Reset wird hier uebergeben
            pi_writeEnable => s_we,
            pi_readRegAddr1 => s_readRegAddr1,
            pi_readRegAddr2 => s_readRegAddr2,
            pi_writeRegAddr => s_writeRegAddr,
            pi_writeRegData => s_writeRegData_32,
            po_readRegData1 => s_readRegData1_32,
            po_readRegData2 => s_readRegData2_32
        );

    -- Testprozess mit Assertions
    test_process : process
    begin
        -- Reset setzten
        s_rst <= '1';
        wait for clk_period;
        s_rst <= '0';
        
        -- Test 1: Versuchen die 0 Vektoren zu lesen
        s_readRegAddr1 <= "10000";
        s_readRegAddr2 <= "11000";
        s_writeRegAddr <= "11100";
        --s_writeRegData <= "0000000010100101";
        s_writeRegData_32 <= "00000000000000000000000010100101"; -- 0xA5
        wait for clk_period;
        --assert (s_readRegData1 = "0000000000000000") report "Reading Out1 after reset not right" severity error;
        --assert (s_readRegData2 = "0000000000000000") report "Reading Out2 after reset not right" severity error;
        assert (s_readRegData1_32 = "00000000000000000000000000000000") report "Reading Out1_32 after reset not right" severity error;
        assert (s_readRegData2_32 = "00000000000000000000000000000000") report "Reading Out2_32 after reset not right" severity error;

        -- Schreiben von 0xA5 in Register 0x4
        s_we <= '1';
        wait for clk_period;
        s_we <= '0';

        -- Test 2: Versuchen die geschriebenen 0x4 Adresse zu lesen
        s_readRegAddr1 <= "11100";
        wait for clk_period;
        --assert (s_readRegData1 = "0000000010100101") report "Reading Out1 after writing not right" severity error;
        --assert (s_readRegData2 = "0000000000000000") report "Reading Out2 after writing not right" severity error;
        assert (s_readRegData1_32 = "00000000000000000000000010100101") report "Reading Out1_32 after writing not right" severity error;
        assert (s_readRegData2_32 = "00000000000000000000000000000000") report "Reading Out2_32 after writing not right" severity error;

        -- Schreiben von 0x1 in Register 0x1
        s_writeRegAddr <= "10000";
        --s_writeRegData <= "0000000000000001";
        s_writeRegData_32 <= "00000000000000000000000000000001";
        s_we <= '1';
        wait for clk_period;
        s_readRegAddr2 <= "10000";
        wait for clk_period;

        -- Test 3: Versuchen die geschriebenen Werte in Out2 auszugeben
        --assert (s_readRegData1 = "0000000010100101") report "Reading Out1 after number 2 writing not right" severity error;
        --assert (s_readRegData2 = "0000000000000001") report "Reading Out2 after number 2 writing not right" severity error;
        assert (s_readRegData1_32 = "00000000000000000000000010100101") report "Reading Out1_32 after number 2 writing not right" severity error;
        assert (s_readRegData2_32 = "00000000000000000000000000000001") report "Reading Out2_32 after writing number 2 not right" severity error;

        -- Nochmals reset testen
        s_rst <= '1';
        wait for clk_period;
        s_rst <= '0';
        --assert (s_readRegData1 = "0000000000000000") report "Reading Out1 after reset not right" severity error;
        --assert (s_readRegData2 = "0000000000000000") report "Reading Out2 after reset not right" severity error;
        assert (s_readRegData1_32 = "00000000000000000000000000000000") report "Reading Out1_32 after reset not right" severity error;
        assert (s_readRegData2_32 = "00000000000000000000000000000000") report "Reading Out2_32 after reset not right" severity error;

        report "Alle Tests erfolgreich abgeschlossen." severity note;

        wait;
    end process;
end architecture behavior;

Skripts/Registerfile/register_file_tb.vcd
$date
  Tue May 20 10:43:08 2025
$end
$version
  GHDL v0
$end
$timescale
  1 fs
$end
$scope module standard $end
$upscope $end
$scope module textio $end
$upscope $end
$scope module std_logic_1164 $end
$upscope $end
$scope module numeric_std $end
$upscope $end
$scope module math_real $end
$upscope $end
$scope module constant_package $end
$upscope $end
$scope module types $end
$upscope $end
$scope module register_file_tb $end
$var reg 1 ! s_clk $end
$var reg 1 " s_rst $end
$var reg 1 # s_we $end
$var reg 5 $ s_readregaddr1[4:0] $end
$var reg 5 % s_readregaddr2[4:0] $end
$var reg 5 & s_writeregaddr[4:0] $end
$var reg 32 ' s_writeregdata_32[31:0] $end
$var reg 32 ( s_readregdata1_32[31:0] $end
$var reg 32 ) s_readregdata2_32[31:0] $end
$scope module dut2 $end
$var reg 1 * pi_clk $end
$var reg 1 + pi_rst $end
$var reg 1 , pi_writeenable $end
$var reg 5 - pi_readregaddr1[4:0] $end
$var reg 5 . pi_readregaddr2[4:0] $end
$var reg 5 / pi_writeregaddr[4:0] $end
$var reg 32 0 pi_writeregdata[31:0] $end
$var reg 32 1 po_readregdata1[31:0] $end
$var reg 32 2 po_readregdata2[31:0] $end
$comment po_registerout is not handled $end
$comment reg_array is not handled $end
$upscope $end
$upscope $end
$enddefinitions $end
#0
0!
1"
0#
b00000 $
b00000 %
b00000 &
b00000000000000000000000000000000 '
b00000000000000000000000000000000 (
b00000000000000000000000000000000 )
0*
1+
0,
b00000 -
b00000 .
b00000 /
b00000000000000000000000000000000 0
b00000000000000000000000000000000 1
b00000000000000000000000000000000 2
#5000000
1!
1*
#10000000
0!
0"
b00001 $
b00010 %
b00011 &
b00000000000000000000000010100101 '
0*
0+
b00001 -
b00010 .
b00011 /
b00000000000000000000000010100101 0
#15000000
1!
b00000000000000000000000000001001 (
b00000000000000000000000000001000 )
1*
b00000000000000000000000000001001 1
b00000000000000000000000000001000 2
#20000000
0!
1#
0*
1,
#25000000
1!
1*
#30000000
0!
0#
b00011 $
0*
0,
b00011 -
#35000000
1!
b00000000000000000000000010100101 (
1*
b00000000000000000000000010100101 1
#40000000
0!
1#
b00001 &
b00000000000000000000000000000001 '
0*
1,
b00001 /
b00000000000000000000000000000001 0
#45000000
1!
1*
#50000000
0!
b00001 %
0*
b00001 .
#55000000
1!
b00000000000000000000000000000001 )
1*
b00000000000000000000000000000001 2
#60000000
0!
1"
b00000000000000000000000000000000 (
b00000000000000000000000000000000 )
0*
1+
b00000000000000000000000000000000 1
b00000000000000000000000000000000 2
#65000000
1!
1*
#70000000
0!
0"
0*
0+
#75000000
1!
b00000000000000000000000000001001 )
1*
b00000000000000000000000000001001 2
#80000000
0!
0*
#85000000
1!
b00000000000000000000000000000001 )
1*
b00000000000000000000000000000001 2
