Komponenten/RAM/Single_Port_RAM.vhdl
library ieee;
use ieee.std_logic_1164.all;
use ieee.numeric_std.all;
use work.constant_package.all;

entity Single_Port_RAM is
    generic (
        word_width : integer := WORD_WIDTH;
        address_width : integer := ADR_WIDTH
    );
    port (
        pi_clk : in std_logic;
        pi_we : in std_logic := '0';
        pi_rst : in std_logic;
        pi_add : in std_logic_vector(address_width - 1 downto 0) := (others => '0');
        pi_data : in std_logic_vector(word_width - 1 downto 0) := (others => '0');
        po_data : out std_logic_vector(word_width - 1 downto 0) := (others => '0')
    );
end entity Single_Port_RAM;
-- alles untere von Copilot abi
architecture behaviour of Single_Port_RAM is
    type memory is array (0 to 2 ** address_width - 1) of std_logic_vector (word_width - 1 downto 0);
    signal regs : memory := (others => (others => '0'));
begin
    process (pi_clk, pi_rst)
    begin
        if pi_rst = '1' then
            regs <= (others => (others => '0'));
            po_data <= (others => '0');
        elsif rising_edge(pi_clk) then
            if pi_we = '1' then
                regs(to_integer(unsigned(pi_add))) <= pi_data;
            end if;
            po_data <= regs(to_integer(unsigned(pi_add)));
        end if;
    end process;
end architecture behaviour;

Testbenches/RAM/Single_Port_RAM_tb.vhdl
library IEEE;
use IEEE.STD_LOGIC_1164.all;
use IEEE.NUMERIC_STD.all;
use work.constant_package.all;

entity Single_Port_RAM_tb is
end Single_Port_RAM_tb;

architecture behavior of Single_Port_RAM_tb is
    signal s_clk : std_logic := '0';
    signal s_rst : std_logic := '0'; -- Reset-Signal
    signal s_we : std_logic := '0';
    signal s_add : std_logic_vector(16 - 1 downto 0);
    signal s_datain : std_logic_vector(16 - 1 downto 0);
    signal s_dataout : std_logic_vector(16 - 1 downto 0);

    -- Taktprozess fuer Simulation
    constant clk_period : time := 10 ns;
begin
    clk_process : process
    begin
        s_clk <= '0';
        wait for clk_period / 2;
        s_clk <= '1';
        wait for clk_period / 2;
    end process;

    -- Instanz des RAM-Moduls
    uut : entity work.Single_Port_RAM
        generic map(16, 16)
        port map(
            pi_clk => s_clk,
            pi_rst => s_rst, -- Reset wird hier uebergeben
            pi_we => s_we,
            pi_add => s_add,
            pi_data => s_datain,
            po_data => s_dataout
        );

    -- Testprozess mit Assertions
    test_process : process
    begin
        -- Test 1: Setze Reset
        s_rst <= '1';
        wait for clk_period;
        s_rst <= '0';

        -- Test 2: Schreibe Wert 0xA5 an Adresse 0x2
        s_add <= "0000000000000010";
        s_datain <= "0000000010100101"; -- 0xA5
        s_we <= '1';
        wait for clk_period;
        s_we <= '0';

        -- Test 3: Lese von Adresse 0x2
        wait for clk_period;
        assert s_dataout = "0000000010100101"
        report "Fehler: Speicherinhalt an Adresse 0x2 sollte 0xA5 sein!"
            severity error;

        -- Test 4: Setze Reset und ueberpruefe den Inhalt
        s_rst <= '1';
        wait for clk_period;
        assert s_dataout = "0000000000000000"
        report "Fehler: Nach Reset sollte der Speicherinhalt 0 sein!"
            severity error;
        s_rst <= '0';

        -- Test 5: Schreibe neuen Wert an Adresse 0x2
        s_add <= "0000000000000010";
        s_datain <= "0000000001010101"; -- 0x55
        s_we <= '1';
        wait for clk_period;
        s_we <= '0';

        -- Test 6: Lese von Adresse 0x2 erneut
        wait for clk_period;
        assert s_dataout = "0000000001010101"
        report "Fehler: Speicherinhalt an Adresse 0x2 sollte 0x55 sein!"
            severity error;

        report "Alle Tests erfolgreich abgeschlossen." severity note;
        wait;
    end process;
end behavior;

Skripts/RAM/Single_Port_RAM_tb.vcd
$date
  Sun May  4 16:27:34 2025
$end
$version
  GHDL v0
$end
$timescale
  1 fs
$end
$scope module standard $end
$upscope $end
$scope module textio $end
$upscope $end
$scope module std_logic_1164 $end
$upscope $end
$scope module numeric_std $end
$upscope $end
$scope module constant_package $end
$upscope $end
$scope module single_port_ram_tb $end
$var reg 1 ! s_clk $end
$var reg 1 " s_rst $end
$var reg 1 # s_we $end
$var reg 16 $ s_add[15:0] $end
$var reg 16 % s_datain[15:0] $end
$var reg 16 & s_dataout[15:0] $end
$scope module uut $end
$var reg 1 ' pi_clk $end
$var reg 1 ( pi_we $end
$var reg 1 ) pi_rst $end
$var reg 16 * pi_add[15:0] $end
$var reg 16 + pi_data[15:0] $end
$var reg 16 , po_data[15:0] $end
$comment regs is not handled $end
$upscope $end
$upscope $end
$enddefinitions $end
#0
0!
1"
0#
bUUUUUUUUUUUUUUUU $
bUUUUUUUUUUUUUUUU %
b0000000000000000 &
0'
0(
1)
bUUUUUUUUUUUUUUUU *
bUUUUUUUUUUUUUUUU +
b0000000000000000 ,
#5000000
1!
1'
#10000000
0!
0"
1#
b0000000000000010 $
b0000000010100101 %
0'
1(
0)
b0000000000000010 *
b0000000010100101 +
#15000000
1!
1'
#20000000
0!
0#
0'
0(
#25000000
1!
b0000000010100101 &
1'
b0000000010100101 ,
#30000000
0!
1"
b0000000000000000 &
0'
1)
b0000000000000000 ,
#35000000
1!
1'
#40000000
0!
0"
1#
b0000000001010101 %
0'
1(
0)
b0000000001010101 +
#45000000
1!
1'
#50000000
0!
0#
0'
0(
#55000000
1!
b0000000001010101 &
1'
b0000000001010101 ,
